{
  "project_info": {
    "project_number": "179448346638",
    "project_id": "wisepotatoapp",
    "storage_bucket": "wisepotatoapp.appspot.com"
  },
  "client": [
    {
      "client_info": {
        "mobilesdk_app_id": "1:179448346638:android:56f4f450097b397045245f",
        "android_client_info": {
          "package_name": "com.wisepotato.wp_app"
        }
      },
      "oauth_client": [
        {
          "client_id": "179448346638-u1mu95n0k3hnbi4isds8om4sn6ib5dch.apps.googleusercontent.com",
          "client_type": 3
        }
      ],
      "api_key": [
        {
          "current_key": "AIzaSyBdLJeUmqYdylowXTMshqk9XuHkgdM2-BQ"
        }
      ],
      "services": {
        "appinvite_service": {
          "other_platform_oauth_client": [
            {
              "client_id": "179448346638-u1mu95n0k3hnbi4isds8om4sn6ib5dch.apps.googleusercontent.com",
              "client_type": 3
            }
          ]
        }
      }
    }
  ],
  "configuration_version": "1"
}